{
  "type": "shape",
  "levels": [
    "Chapter",
    "Verse"
  ],
  "chapters": [
    [
      1,
      0,
      0,
      1,
      0,
      0,
      0,
      0,
      1,
      0,
      1,
      0,
      1,
      0,
      1
    ],
    [
      1,
      0,
      0,
      1,
      0,
      0,
      0,
      1,
      1
    ],
    [
      1,
      1,
      0,
      0,
      1,
      1,
      0,
      0,
      1
    ]
  ],
  "fetchedAt": "2025-10-30T14:42:23.198Z",
  "source": "http://localhost:8000/api/shape/Kovetz%20Al%20Yad%20HaChazakah%20on%20Mishneh%20Torah%2C%20Circumcision"
}
