{
  "title": "Sha'ar HaMelekh on Mishneh Torah, Ritual Slaughter",
  "categories": [
    "Halakhah",
    "Mishneh Torah",
    "Commentary",
    "Sha'ar HaMelekh",
    "Sefer Kedushah"
  ],
  "schema": {
    "nodeType": "JaggedArrayNode",
    "depth": 3,
    "addressTypes": [
      "Integer",
      "Halakhah",
      "Integer"
    ],
    "sectionNames": [
      "Chapter",
      "Halakhah",
      "Comment"
    ],
    "match_templates": [
      {
        "term_slugs": [
          "shaar-hamelekh",
          "hilchot",
          "ritual-slaughter"
        ]
      },
      {
        "term_slugs": [
          "shaar-hamelekh",
          "ritual-slaughter"
        ]
      }
    ],
    "lengths": [
      14,
      4,
      4
    ],
    "titles": [
      {
        "text": "שער המלך על משנה תורה, הלכות שחיטה",
        "lang": "he",
        "primary": true
      },
      {
        "text": "Sha'ar HaMelekh on Mishneh Torah, Ritual Slaughter",
        "lang": "en",
        "primary": true
      }
    ],
    "key": "Sha'ar HaMelekh on Mishneh Torah, Ritual Slaughter"
  },
  "titles": [],
  "fetchedAt": "2025-10-30T14:42:29.008Z",
  "source": "http://localhost:8000/api/v2/raw/index/Sha'ar%20HaMelekh%20on%20Mishneh%20Torah%2C%20Ritual%20Slaughter"
}
