{
  "title": "Maggid Mishneh on Mishneh Torah, Shofar, Sukkah and Lulav",
  "categories": [
    "Halakhah",
    "Mishneh Torah",
    "Commentary",
    "Maggid Mishneh",
    "Sefer Zemanim"
  ],
  "schema": {
    "nodeType": "JaggedArrayNode",
    "depth": 3,
    "addressTypes": [
      "Perek",
      "Halakhah",
      "Integer"
    ],
    "sectionNames": [
      "Chapter",
      "Halakhah",
      "Comment"
    ],
    "match_templates": [
      {
        "term_slugs": [
          "maggid-mishneh",
          "hilchot",
          "shofar-sukkah-and-lulav"
        ]
      },
      {
        "term_slugs": [
          "maggid-mishneh",
          "shofar-sukkah-and-lulav"
        ]
      }
    ],
    "lengths": [
      8,
      117,
      241
    ],
    "titles": [
      {
        "primary": true,
        "text": "מגיד משנה על משנה תורה, הלכות שופר וסוכה ולולב",
        "lang": "he"
      },
      {
        "text": "Maggid Mishneh on Mishneh Torah, Shofar, Sukkah and Lulav",
        "lang": "en",
        "primary": true
      }
    ],
    "key": "Maggid Mishneh on Mishneh Torah, Shofar, Sukkah and Lulav"
  },
  "titles": [],
  "fetchedAt": "2025-10-30T14:42:24.991Z",
  "source": "http://localhost:8000/api/v2/raw/index/Maggid%20Mishneh%20on%20Mishneh%20Torah%2C%20Shofar%2C%20Sukkah%20and%20Lulav"
}
