{
  "title": "Ohr Sameach on Mishneh Torah, One Who Injures a Person or Property",
  "categories": [
    "Halakhah",
    "Mishneh Torah",
    "Commentary",
    "Ohr Sameach",
    "Sefer Nezikim"
  ],
  "schema": {
    "nodeType": "JaggedArrayNode",
    "depth": 3,
    "addressTypes": [
      "Integer",
      "Halakhah",
      "Integer"
    ],
    "sectionNames": [
      "Chapter",
      "Halakhah",
      "Comment"
    ],
    "match_templates": [
      {
        "term_slugs": [
          "ohr-sameach",
          "hilchot",
          "one-who-injures-a-person-or-property"
        ]
      },
      {
        "term_slugs": [
          "ohr-sameach",
          "one-who-injures-a-person-or-property"
        ]
      }
    ],
    "lengths": [
      8,
      14,
      14
    ],
    "titles": [
      {
        "primary": true,
        "text": "אור שמח על משנה תורה, הלכות חובל ומזיק",
        "lang": "he"
      },
      {
        "text": "Ohr Sameach on Mishneh Torah, One Who Injures a Person or Property",
        "lang": "en",
        "primary": true
      }
    ],
    "key": "Ohr Sameach on Mishneh Torah, One Who Injures a Person or Property"
  },
  "titles": [],
  "fetchedAt": "2025-10-30T14:42:28.549Z",
  "source": "http://localhost:8000/api/v2/raw/index/Ohr%20Sameach%20on%20Mishneh%20Torah%2C%20One%20Who%20Injures%20a%20Person%20or%20Property"
}
