{
  "type": "shape",
  "levels": [
    "Chapter",
    "Verse"
  ],
  "chapters": [
    [
      5,
      7,
      2,
      6,
      2,
      11,
      3
    ],
    [
      12,
      3,
      4,
      2,
      2
    ],
    [
      4,
      7,
      2,
      9,
      3,
      3,
      7,
      9,
      8,
      3
    ],
    [
      23,
      6,
      4,
      2,
      2,
      3,
      3,
      2,
      2,
      5
    ],
    [
      4,
      6,
      7,
      5,
      2,
      3
    ],
    [
      8,
      5,
      2,
      3,
      3,
      6,
      2,
      4
    ],
    [
      9,
      4,
      2,
      7,
      4,
      3,
      9,
      3
    ],
    [
      13,
      3,
      6,
      2
    ]
  ],
  "fetchedAt": "2025-10-30T14:42:14.672Z",
  "source": "http://localhost:8000/api/shape/Jerusalem%20Talmud%20Shevuot"
}
