{
  "title": "Hasagot HaRa'avad on Mishneh Torah, Plaintiff and Defendant",
  "categories": [
    "Halakhah",
    "Mishneh Torah",
    "Commentary",
    "Hasagot HaRa'avad",
    "Sefer Mishpatim"
  ],
  "schema": {
    "nodeType": "JaggedArrayNode",
    "depth": 3,
    "addressTypes": [
      "Perek",
      "Halakhah",
      "Integer"
    ],
    "sectionNames": [
      "Chapter",
      "Halakhah",
      "Comment"
    ],
    "match_templates": [
      {
        "term_slugs": [
          "hasagot-haraavad",
          "hilchot",
          "plaintiff-and-defendant"
        ]
      },
      {
        "term_slugs": [
          "hasagot-haraavad",
          "plaintiff-and-defendant"
        ]
      }
    ],
    "lengths": [
      16,
      31,
      32
    ],
    "titles": [
      {
        "primary": true,
        "text": "השגות הראב\"ד על משנה תורה, הלכות טוען ונטען",
        "lang": "he"
      },
      {
        "text": "Hasagot HaRa'avad on Mishneh Torah, Plaintiff and Defendant",
        "lang": "en",
        "primary": true
      }
    ],
    "key": "Hasagot HaRa'avad on Mishneh Torah, Plaintiff and Defendant"
  },
  "titles": [],
  "fetchedAt": "2025-10-30T14:42:21.566Z",
  "source": "http://localhost:8000/api/v2/raw/index/Hasagot%20HaRa'avad%20on%20Mishneh%20Torah%2C%20Plaintiff%20and%20Defendant"
}
