{
  "title": "Yitzchak Yeranen on Mishneh Torah, Vows",
  "categories": [
    "Halakhah",
    "Mishneh Torah",
    "Commentary",
    "Yitzchak Yeranen",
    "Sefer Haflaah"
  ],
  "schema": {
    "nodeType": "JaggedArrayNode",
    "depth": 3,
    "addressTypes": [
      "Integer",
      "Halakhah",
      "Integer"
    ],
    "sectionNames": [
      "Chapter",
      "Halakhah",
      "Comment"
    ],
    "match_templates": [
      {
        "term_slugs": [
          "yitzchak-yeranen",
          "hilchot",
          "vows"
        ]
      },
      {
        "term_slugs": [
          "yitzchak-yeranen",
          "vows"
        ]
      }
    ],
    "lengths": [
      13,
      6,
      6
    ],
    "titles": [
      {
        "lang": "he",
        "text": "יצחק ירנן על משנה תורה, הלכות נדרים",
        "primary": true
      },
      {
        "text": "Yitzchak Yeranen on Mishneh Torah, Vows",
        "lang": "en",
        "primary": true
      }
    ],
    "key": "Yitzchak Yeranen on Mishneh Torah, Vows"
  },
  "titles": [],
  "fetchedAt": "2025-10-30T14:42:32.848Z",
  "source": "http://localhost:8000/api/v2/raw/index/Yitzchak%20Yeranen%20on%20Mishneh%20Torah%2C%20Vows"
}
