{
  "title": "Tzafnat Pa'neach on Mishneh Torah, Repentance",
  "categories": [
    "Halakhah",
    "Mishneh Torah",
    "Commentary",
    "Tzafnat Pa'neach",
    "Sefer Madda"
  ],
  "schema": {
    "nodeType": "JaggedArrayNode",
    "depth": 3,
    "addressTypes": [
      "Integer",
      "Halakhah",
      "Integer"
    ],
    "sectionNames": [
      "Chapter",
      "Halakhah",
      "Comment"
    ],
    "match_templates": [
      {
        "term_slugs": [
          "tzafnat-paneach",
          "hilchot",
          "repentance"
        ]
      },
      {
        "term_slugs": [
          "tzafnat-paneach",
          "repentance"
        ]
      }
    ],
    "lengths": [
      10,
      17,
      22
    ],
    "titles": [
      {
        "text": "צפנת פענח על משנה תורה, הלכות תשובה",
        "lang": "he",
        "primary": true
      },
      {
        "text": "Tzafnat Pa'neach on Mishneh Torah, Repentance",
        "lang": "en",
        "primary": true
      }
    ],
    "key": "Tzafnat Pa'neach on Mishneh Torah, Repentance"
  },
  "titles": [],
  "fetchedAt": "2025-10-30T14:42:30.629Z",
  "source": "http://localhost:8000/api/v2/raw/index/Tzafnat%20Pa'neach%20on%20Mishneh%20Torah%2C%20Repentance"
}
